repo2wasm/__init__.py
repo2wasm/binder.py
repo2wasm/cli.py
repo2wasm/repo2wasm.py
repo2wasm/buildpacks/__init__.py
repo2wasm/buildpacks/base.py
repo2wasm/buildpacks/conda.py
repo2wasm/buildpacks/exceptions.py
repo2wasm/buildpacks/install.py
repo2wasm/buildpacks/requirements.py
repo2wasm/buildpacks/test_utils.py
repo2wasm/buildpacks/utils.py
repo2wasm-0.5.1.dist-info/METADATA
repo2wasm-0.5.1.dist-info/WHEEL
repo2wasm-0.5.1.dist-info/entry_points.txt
repo2wasm-0.5.1.dist-info/licenses/LICENSE
repo2wasm-0.5.1.dist-info/RECORD
